cclog/__init__.py
cclog/cclog.py
cclog/log.yaml
cclog-1.0.dist-info/METADATA
cclog-1.0.dist-info/WHEEL
cclog-1.0.dist-info/top_level.txt
cclog-1.0.dist-info/RECORD
