Metadata-Version: 2.1
Name: cclog
Version: 1.0
Summary: chen's log config package
Author: chen
Author-email: 690246265@qq.com
License: apache 3.0
Requires: yaml
Requires: logging
